pyssh_util/__init__.py
pyssh_util/ssh_util.py
pyssh_util-1.0.3.dist-info/LICENSE
pyssh_util-1.0.3.dist-info/METADATA
pyssh_util-1.0.3.dist-info/WHEEL
pyssh_util-1.0.3.dist-info/top_level.txt
pyssh_util-1.0.3.dist-info/zip-safe
pyssh_util-1.0.3.dist-info/RECORD
