Metadata-Version: 2.1
Name: pyssh_util
Version: 1.0.3
Summary: ssh助手
Home-page: https://github.com/buyfakett
Author: buyfakett
Author-email: buyfakett@vip.qq.com
License: MIT
Requires-Python: >=3.6
License-File: LICENSE
Requires-Dist: paramiko
